{
  "Version": 3,
  "Meta": {
    "Duration": 7.97,
    "Fps": 30.0,
    "Loop": true,
    "AreBeziersRestricted": true,
    "CurveCount": 59,
    "TotalSegmentCount": 427,
    "TotalPointCount": 823,
    "UserDataCount": 1,
    "TotalUserDataSize": 0
  },
  "Curves": [
    {
      "Target": "Parameter",
      "Id": "ParamAngleX",
      "Segments": [
        0,
        0,
        1,
        0.178,
        0,
        0.355,
        1.44,
        0.533,
        6,
        1,
        0.711,
        10.56,
        0.889,
        14,
        1.067,
        14,
        1,
        1.589,
        14,
        2.111,
        13.438,
        2.633,
        9,
        1,
        2.844,
        7.206,
        3.056,
        -22,
        3.267,
        -22,
        1,
        3.422,
        -22,
        3.578,
        -9.244,
        3.733,
        -1.285,
        1,
        3.911,
        7.81,
        4.089,
        9,
        4.267,
        9,
        1,
        4.434,
        9,
        4.6,
        1.957,
        4.767,
        0.97,
        1,
        4.956,
        -0.149,
        5.144,
        0.087,
        5.333,
        -1.02,
        1,
        5.5,
        -1.997,
        5.666,
        -8,
        5.833,
        -8,
        0,
        6.533,
        2.007,
        0,
        7.367,
        2,
        2,
        7.967,
        2
      ]
    },
    {
      "Target": "Parameter",
      "Id": "ParamAngleY",
      "Segments": [
        0,
        0,
        1,
        0.089,
        0,
        0.178,
        -12.427,
        0.267,
        -13.8,
        1,
        0.356,
        -15.173,
        0.444,
        -15,
        0.533,
        -15,
        2,
        1.067,
        -15,
        0,
        2.633,
        -16,
        0,
        3.267,
        0,
        2,
        3.633,
        0,
        0,
        4.267,
        -16,
        0,
        4.9,
        0,
        2,
        5.267,
        0,
        0,
        5.833,
        -15,
        0,
        7.367,
        -10,
        2,
        7.967,
        -10
      ]
    },
    {
      "Target": "Parameter",
      "Id": "ParamAngleZ",
      "Segments": [
        0,
        0,
        0,
        0.7,
        -26,
        0,
        1.167,
        -3.29,
        0,
        1.733,
        -25.994,
        1,
        1.878,
        -25.994,
        2.022,
        -25.011,
        2.167,
        -21.35,
        1,
        2.245,
        -19.379,
        2.322,
        -16.868,
        2.4,
        -12.03,
        1,
        2.478,
        -7.192,
        2.555,
        11,
        2.633,
        11,
        0,
        3.4,
        -0.06,
        0,
        4.267,
        11,
        0,
        4.9,
        0,
        0,
        5.233,
        0.51,
        0,
        6.633,
        -29,
        0,
        7.367,
        8.63,
        2,
        7.967,
        8.63
      ]
    },
    {
      "Target": "Parameter",
      "Id": "ParamEyeLOpen",
      "Segments": [
        0,
        1,
        1,
        0.167,
        0.996,
        0.333,
        0.004,
        0.5,
        0,
        1,
        0.844,
        0.001,
        1.189,
        0.739,
        1.533,
        0.74,
        1,
        1.7,
        0.74,
        1.866,
        0.699,
        2.033,
        0.61,
        1,
        2.211,
        0.513,
        2.389,
        0.366,
        2.567,
        0.278,
        1,
        2.911,
        0.094,
        3.256,
        0,
        3.6,
        0,
        2,
        3.633,
        0,
        1,
        3.711,
        -0.008,
        3.789,
        1.008,
        3.867,
        1,
        1,
        3.922,
        1,
        3.978,
        0.94,
        4.033,
        0.905,
        1,
        4.089,
        0.864,
        4.144,
        0.819,
        4.2,
        0.773,
        1,
        4.311,
        0.682,
        4.422,
        0.584,
        4.533,
        0.494,
        1,
        4.766,
        0.314,
        5,
        0.131,
        5.233,
        0.002,
        3,
        5.267,
        0,
        1,
        5.345,
        -0.008,
        5.422,
        1.008,
        5.5,
        1,
        2,
        5.967,
        1,
        1,
        6.011,
        1.008,
        6.056,
        -0.008,
        6.1,
        0,
        1,
        6.144,
        0,
        6.189,
        0.318,
        6.233,
        0.531,
        1,
        6.255,
        0.635,
        6.278,
        0.718,
        6.3,
        0.72,
        1,
        6.333,
        0.724,
        6.367,
        0.726,
        6.4,
        0.727,
        1,
        6.511,
        0.731,
        6.622,
        0.737,
        6.733,
        0.74,
        1,
        6.944,
        0.747,
        7.156,
        0.748,
        7.367,
        0.75,
        2,
        7.967,
        0.75
      ]
    },
    {
      "Target": "Parameter",
      "Id": "ParamEyeLSmile",
      "Segments": [
        0,
        0,
        2,
        0.5,
        0,
        1,
        0.667,
        0,
        0.833,
        0.237,
        1,
        0.46,
        1,
        1.156,
        0.668,
        1.311,
        0.926,
        1.467,
        0.942,
        1,
        1.667,
        0.963,
        1.867,
        0.97,
        2.067,
        0.979,
        1,
        2.156,
        0.983,
        2.244,
        0.984,
        2.333,
        0.986,
        1,
        2.355,
        0.987,
        2.378,
        0.987,
        2.4,
        0.988,
        1,
        2.433,
        0.989,
        2.467,
        0.989,
        2.5,
        0.99,
        1,
        2.556,
        0.991,
        2.611,
        0.992,
        2.667,
        0.993,
        1,
        2.711,
        0.994,
        2.756,
        0.994,
        2.8,
        0.995,
        0,
        2.9,
        0.996,
        0,
        2.967,
        0.997,
        0,
        3.033,
        0.998,
        2,
        3.1,
        0.998,
        0,
        3.167,
        0.999,
        2,
        3.267,
        0.999,
        0,
        3.367,
        1,
        2,
        3.633,
        1,
        0,
        3.867,
        0,
        1,
        3.878,
        0,
        3.889,
        -0.005,
        3.9,
        0.002,
        1,
        4.344,
        0.296,
        4.789,
        0.704,
        5.233,
        0.998,
        1,
        5.244,
        1.005,
        5.256,
        1,
        5.267,
        1,
        0,
        5.5,
        0,
        1,
        5.511,
        0,
        5.522,
        -0.002,
        5.533,
        0.001,
        1,
        5.722,
        0.059,
        5.911,
        0.147,
        6.1,
        0.23,
        1,
        6.144,
        0.249,
        6.189,
        0.29,
        6.233,
        0.32,
        1,
        6.266,
        0.343,
        6.3,
        0.365,
        6.333,
        0.39,
        1,
        6.366,
        0.415,
        6.4,
        0.444,
        6.433,
        0.47,
        1,
        6.478,
        0.504,
        6.522,
        0.537,
        6.567,
        0.57,
        1,
        6.622,
        0.611,
        6.678,
        0.652,
        6.733,
        0.69,
        1,
        6.755,
        0.705,
        6.778,
        0.711,
        6.8,
        0.73,
        1,
        6.989,
        0.89,
        7.178,
        0.983,
        7.367,
        0.983,
        2,
        7.967,
        0.983
      ]
    },
    {
      "Target": "Parameter",
      "Id": "ParamEyeROpen",
      "Segments": [
        0,
        1,
        1,
        0.167,
        0.996,
        0.333,
        0.004,
        0.5,
        0,
        1,
        0.667,
        -0.001,
        0.833,
        0.135,
        1,
        0.387,
        1,
        1.178,
        0.631,
        1.355,
        0.75,
        1.533,
        0.75,
        1,
        1.7,
        0.75,
        1.866,
        0.708,
        2.033,
        0.616,
        1,
        2.211,
        0.503,
        2.389,
        0.368,
        2.567,
        0.278,
        1,
        2.911,
        0.095,
        3.256,
        0,
        3.6,
        0,
        2,
        3.633,
        0,
        1,
        3.711,
        -0.008,
        3.789,
        1.008,
        3.867,
        1,
        1,
        3.922,
        1,
        3.978,
        0.94,
        4.033,
        0.905,
        1,
        4.089,
        0.864,
        4.144,
        0.819,
        4.2,
        0.773,
        1,
        4.311,
        0.682,
        4.422,
        0.584,
        4.533,
        0.494,
        1,
        4.766,
        0.314,
        5,
        0.131,
        5.233,
        0.002,
        3,
        5.267,
        0,
        1,
        5.345,
        -0.008,
        5.422,
        1.008,
        5.5,
        1,
        2,
        5.967,
        1,
        1,
        6.011,
        1.008,
        6.056,
        -0.008,
        6.1,
        0,
        1,
        6.144,
        -0.003,
        6.189,
        0.394,
        6.233,
        0.47,
        1,
        6.289,
        0.568,
        6.344,
        0.648,
        6.4,
        0.656,
        1,
        6.511,
        0.674,
        6.622,
        0.683,
        6.733,
        0.693,
        1,
        6.944,
        0.713,
        7.156,
        0.72,
        7.367,
        0.72,
        2,
        7.967,
        0.72
      ]
    },
    {
      "Target": "Parameter",
      "Id": "ParamEyeRSmile",
      "Segments": [
        0,
        0,
        2,
        0.5,
        0,
        0,
        1.5,
        1,
        2,
        3.633,
        1,
        0,
        3.867,
        0,
        1,
        3.878,
        0,
        3.889,
        -0.005,
        3.9,
        0.002,
        1,
        4.344,
        0.296,
        4.789,
        0.704,
        5.233,
        0.998,
        1,
        5.244,
        1.005,
        5.256,
        1,
        5.267,
        1,
        0,
        5.5,
        0,
        1,
        5.511,
        0,
        5.522,
        -0.003,
        5.533,
        0.001,
        1,
        5.8,
        0.104,
        6.066,
        0.257,
        6.333,
        0.4,
        1,
        6.411,
        0.442,
        6.489,
        0.513,
        6.567,
        0.57,
        1,
        6.589,
        0.586,
        6.611,
        0.603,
        6.633,
        0.62,
        1,
        6.678,
        0.653,
        6.722,
        0.69,
        6.767,
        0.72,
        1,
        6.8,
        0.743,
        6.834,
        0.753,
        6.867,
        0.78,
        1,
        7.034,
        0.913,
        7.2,
        0.993,
        7.367,
        0.993,
        2,
        7.967,
        0.993
      ]
    },
    {
      "Target": "Parameter",
      "Id": "ParamEyeBallX",
      "Segments": [
        0,
        0,
        0,
        0.5,
        0.28,
        2,
        1.5,
        0.28,
        1,
        1.689,
        0.28,
        1.878,
        0.179,
        2.067,
        -0.03,
        1,
        2.311,
        -0.301,
        2.556,
        -0.44,
        2.8,
        -0.44,
        2,
        4.433,
        -0.44,
        1,
        4.6,
        -0.44,
        4.766,
        -0.37,
        4.933,
        -0.24,
        1,
        4.966,
        -0.214,
        5,
        -0.193,
        5.033,
        -0.17,
        1,
        5.066,
        -0.147,
        5.1,
        -0.124,
        5.133,
        -0.1,
        1,
        5.178,
        -0.068,
        5.222,
        -0.038,
        5.267,
        0,
        1,
        5.456,
        0.161,
        5.644,
        0.25,
        5.833,
        0.25,
        0,
        6.6,
        -0.08,
        2,
        7.367,
        -0.08,
        2,
        7.967,
        -0.08
      ]
    },
    {
      "Target": "Parameter",
      "Id": "ParamEyeBallY",
      "Segments": [
        0,
        0,
        0,
        0.5,
        -0.04,
        2,
        1.5,
        -0.04,
        0,
        2.633,
        0.54,
        1,
        2.789,
        0.54,
        2.944,
        0.468,
        3.1,
        0.3,
        1,
        3.278,
        0.108,
        3.455,
        0,
        3.633,
        0,
        0,
        4.267,
        0.54,
        1,
        4.422,
        0.54,
        4.578,
        0.468,
        4.733,
        0.3,
        1,
        4.911,
        0.108,
        5.089,
        0,
        5.267,
        0,
        0,
        5.833,
        0.58,
        2,
        7.367,
        0.58,
        2,
        7.967,
        0.58
      ]
    },
    {
      "Target": "Parameter",
      "Id": "ParamBrowLForm",
      "Segments": [
        0,
        0,
        2,
        5.267,
        0,
        0,
        5.8,
        0.48,
        0,
        6.367,
        0,
        2,
        7.367,
        0,
        2,
        7.967,
        0
      ]
    },
    {
      "Target": "Parameter",
      "Id": "ParamBrowRForm",
      "Segments": [
        0,
        0,
        2,
        5.267,
        0,
        0,
        5.8,
        0.44,
        0,
        6.367,
        0,
        2,
        7.367,
        0,
        2,
        7.967,
        0
      ]
    },
    {
      "Target": "Parameter",
      "Id": "ParamMouthForm",
      "Segments": [
        0,
        1,
        0,
        7.367,
        -0.75,
        2,
        7.967,
        -0.75
      ]
    },
    {
      "Target": "Parameter",
      "Id": "ParamMouthOpenY",
      "Segments": [
        0,
        1,
        2,
        0.1,
        1,
        1,
        0.111,
        1.052,
        0.122,
        0.6,
        0.133,
        0.675,
        1,
        0.166,
        0.659,
        0.2,
        0.959,
        0.233,
        1,
        2,
        0.267,
        1,
        2,
        0.3,
        0.941,
        1,
        0.311,
        0.86,
        0.322,
        0.765,
        0.333,
        0.769,
        1,
        0.344,
        0.766,
        0.356,
        0.827,
        0.367,
        0.906,
        1,
        0.378,
        1.063,
        0.389,
        0.976,
        0.4,
        1,
        2,
        0.7,
        1,
        1,
        0.711,
        1.669,
        0.722,
        -0.181,
        0.733,
        0.063,
        1,
        0.778,
        0.058,
        0.822,
        0.711,
        0.867,
        0.706,
        1,
        0.889,
        0.695,
        0.911,
        0.011,
        0.933,
        0,
        1,
        0.955,
        0.004,
        0.978,
        1.048,
        1,
        1,
        1,
        1.022,
        1.053,
        1.045,
        0.282,
        1.067,
        0.282,
        1,
        1.078,
        0.272,
        1.089,
        0.514,
        1.1,
        0.722,
        1,
        1.111,
        1.022,
        1.122,
        1.012,
        1.133,
        1,
        1,
        1.144,
        1.034,
        1.156,
        0.987,
        1.167,
        0.675,
        1,
        1.178,
        0.445,
        1.189,
        0.177,
        1.2,
        0.188,
        1,
        1.222,
        0.19,
        1.245,
        0.312,
        1.267,
        0.314,
        1,
        1.289,
        0.309,
        1.311,
        0.02,
        1.333,
        0.016,
        1,
        1.366,
        -0.063,
        1.4,
        0.756,
        1.433,
        1,
        2,
        1.633,
        1,
        1,
        1.644,
        1.632,
        1.656,
        -0.117,
        1.667,
        0.11,
        1,
        1.7,
        0.006,
        1.734,
        0.903,
        1.767,
        1,
        2,
        1.967,
        1,
        1,
        1.978,
        1.712,
        1.989,
        -0.263,
        2,
        0.031,
        1,
        2.011,
        0.018,
        2.022,
        0.295,
        2.033,
        0.649,
        3,
        2.067,
        1,
        2,
        2.267,
        1,
        2,
        2.3,
        0.865,
        1,
        2.311,
        0.705,
        2.322,
        0.61,
        2.333,
        0.612,
        1,
        2.344,
        0.56,
        2.356,
        0.931,
        2.367,
        1,
        2,
        2.533,
        1,
        2,
        2.567,
        0.751,
        1,
        2.578,
        0.419,
        2.589,
        0.16,
        2.6,
        0.173,
        1,
        2.611,
        0.165,
        2.622,
        0.325,
        2.633,
        0.53,
        1,
        2.644,
        0.678,
        2.656,
        1.2,
        2.667,
        1,
        2,
        2.767,
        1,
        1,
        2.778,
        0.878,
        2.789,
        -0.079,
        2.8,
        0.031,
        1,
        2.811,
        -0.246,
        2.822,
        1.704,
        2.833,
        1,
        2,
        2.933,
        1,
        2,
        2.967,
        0.662,
        1,
        2.978,
        0.309,
        2.989,
        0.034,
        3,
        0.047,
        1,
        3.011,
        -0.276,
        3.022,
        1.697,
        3.033,
        1,
        2,
        3.233,
        1,
        1,
        3.266,
        0.638,
        3.3,
        -0.05,
        3.333,
        0,
        2,
        3.867,
        0,
        1,
        3.878,
        -0.013,
        3.889,
        0.252,
        3.9,
        0.591,
        1,
        3.911,
        1.262,
        3.922,
        0.903,
        3.933,
        1,
        2,
        4.133,
        1,
        2,
        4.167,
        0.925,
        1,
        4.178,
        0.636,
        4.189,
        0.299,
        4.2,
        0.314,
        1,
        4.211,
        0.21,
        4.222,
        1.452,
        4.233,
        1,
        2,
        4.3,
        1,
        1,
        4.311,
        1.319,
        4.322,
        0.455,
        4.333,
        0.439,
        1,
        4.355,
        0.441,
        4.378,
        0.578,
        4.4,
        0.58,
        2,
        4.433,
        0.58,
        1,
        4.444,
        0.58,
        4.456,
        0.712,
        4.467,
        0.924,
        3,
        4.5,
        1,
        2,
        4.967,
        1,
        1,
        5,
        0.758,
        5.034,
        -0.082,
        5.067,
        0,
        1,
        5.089,
        0.006,
        5.111,
        0.355,
        5.133,
        0.361,
        1,
        5.178,
        0.362,
        5.222,
        0.187,
        5.267,
        0.188,
        1,
        5.278,
        0.047,
        5.289,
        1.544,
        5.3,
        1,
        2,
        5.367,
        1,
        1,
        5.378,
        1.013,
        5.389,
        1.026,
        5.4,
        0.69,
        1,
        5.411,
        0.982,
        5.422,
        1.035,
        5.433,
        1,
        2,
        5.5,
        1,
        1,
        5.511,
        1.732,
        5.522,
        -0.303,
        5.533,
        0.031,
        1,
        5.544,
        0.018,
        5.556,
        0.283,
        5.567,
        0.622,
        3,
        5.6,
        1,
        2,
        5.733,
        1,
        2,
        5.767,
        0.728,
        1,
        5.778,
        0.4,
        5.789,
        0.144,
        5.8,
        0.157,
        1,
        5.811,
        0.06,
        5.822,
        0.895,
        5.833,
        1,
        2,
        6.033,
        1,
        1,
        6.044,
        0.97,
        6.056,
        1.079,
        6.067,
        0.893,
        1,
        6.078,
        0.791,
        6.089,
        0.693,
        6.1,
        0.604,
        1,
        6.133,
        0.327,
        6.167,
        0.143,
        6.2,
        0.141,
        1,
        6.211,
        0.131,
        6.222,
        0.344,
        6.233,
        0.617,
        1,
        6.244,
        1.094,
        6.256,
        0.985,
        6.267,
        1,
        2,
        6.4,
        1,
        2,
        6.433,
        0.987,
        1,
        6.444,
        0.754,
        6.456,
        0.572,
        6.467,
        0.58,
        1,
        6.478,
        0.507,
        6.489,
        1.281,
        6.5,
        1,
        2,
        6.567,
        1,
        1,
        6.578,
        0.892,
        6.589,
        -0.101,
        6.6,
        0.016,
        1,
        6.611,
        0.003,
        6.622,
        0.268,
        6.633,
        0.606,
        1,
        6.644,
        1.296,
        6.656,
        0.885,
        6.667,
        1,
        2,
        6.767,
        1,
        1,
        6.778,
        1.624,
        6.789,
        -0.103,
        6.8,
        0.125,
        1,
        6.811,
        0.119,
        6.822,
        0.261,
        6.833,
        0.444,
        1,
        6.844,
        0.571,
        6.856,
        1.028,
        6.867,
        1,
        2,
        6.967,
        1,
        1,
        6.978,
        0.802,
        6.989,
        0.067,
        7,
        0.141,
        1,
        7.011,
        0.131,
        7.022,
        0.344,
        7.033,
        0.617,
        1,
        7.044,
        1.094,
        7.056,
        0.985,
        7.067,
        1,
        2,
        7.233,
        1,
        2,
        7.267,
        0.82,
        1,
        7.289,
        0.362,
        7.311,
        -0.003,
        7.333,
        0,
        2,
        7.967,
        0
      ]
    },
    {
      "Target": "Parameter",
      "Id": "ParamArmL",
      "Segments": [
        0,
        0,
        0,
        0.967,
        -6,
        0,
        1.433,
        -1,
        0,
        2.267,
        -6,
        0,
        3.667,
        2,
        1,
        3.9,
        2,
        4.134,
        0.845,
        4.367,
        0,
        1,
        4.711,
        -1.247,
        5.056,
        -1.739,
        5.4,
        -3,
        1,
        5.6,
        -3.732,
        5.8,
        -5,
        6,
        -5,
        1,
        6.2,
        -5,
        6.4,
        -1.846,
        6.6,
        -1,
        1,
        6.844,
        0.033,
        7.089,
        0,
        7.333,
        0,
        2,
        7.967,
        0
      ]
    },
    {
      "Target": "Parameter",
      "Id": "ParamArmL1",
      "Segments": [
        0,
        0,
        0,
        0.967,
        8,
        0,
        1.433,
        5,
        2,
        3.667,
        5,
        1,
        3.9,
        5,
        4.134,
        0.783,
        4.367,
        0,
        1,
        4.678,
        -1.044,
        4.989,
        -1.225,
        5.3,
        -2,
        1,
        5.5,
        -2.498,
        5.7,
        -3,
        5.9,
        -3,
        0,
        6.733,
        0,
        2,
        7.967,
        0
      ]
    },
    {
      "Target": "Parameter",
      "Id": "ParamHandL",
      "Segments": [
        0,
        0,
        0,
        0.967,
        1,
        1,
        1.122,
        1,
        1.278,
        0.694,
        1.433,
        0.26,
        1,
        1.711,
        -0.515,
        1.989,
        -0.83,
        2.267,
        -0.83,
        1,
        2.734,
        -0.83,
        3.2,
        -0.806,
        3.667,
        -0.58,
        1,
        3.9,
        -0.467,
        4.134,
        0,
        4.367,
        0,
        1,
        4.622,
        0,
        4.878,
        -0.011,
        5.133,
        -0.28,
        1,
        5.333,
        -0.49,
        5.533,
        -1,
        5.733,
        -1,
        1,
        6.155,
        -1,
        6.578,
        -0.781,
        7,
        -0.26,
        1,
        7.111,
        -0.123,
        7.222,
        0,
        7.333,
        0,
        2,
        7.967,
        0
      ]
    },
    {
      "Target": "Parameter",
      "Id": "ParamArmR",
      "Segments": [
        0,
        0,
        1,
        0.156,
        0,
        0.311,
        6.394,
        0.467,
        7,
        1,
        1.089,
        9.422,
        1.711,
        10,
        2.333,
        10,
        0,
        5.433,
        -3,
        0,
        6.6,
        5,
        0,
        7.367,
        0,
        2,
        7.967,
        0
      ]
    },
    {
      "Target": "Parameter",
      "Id": "ParamArmR1",
      "Segments": [
        0,
        0,
        0,
        0.467,
        4,
        0,
        1.1,
        -3,
        0,
        2.333,
        6,
        1,
        3.044,
        6,
        3.756,
        3.199,
        4.467,
        0,
        1,
        5.178,
        -3.199,
        5.889,
        -4,
        6.6,
        -4,
        0,
        7.367,
        0,
        2,
        7.967,
        0
      ]
    },
    {
      "Target": "Parameter",
      "Id": "ParamBodyAngleX",
      "Segments": [
        0,
        0,
        0,
        0.5,
        -6,
        0,
        1,
        3,
        0,
        1.5,
        -1,
        0,
        2,
        6,
        0,
        3.267,
        0,
        0,
        4.267,
        2,
        0,
        7.367,
        0,
        2,
        7.967,
        0
      ]
    },
    {
      "Target": "Parameter",
      "Id": "ParamBodyAngleY",
      "Segments": [
        0,
        0,
        0,
        0.567,
        -3,
        2,
        1.133,
        -3,
        1,
        1.544,
        -3,
        1.956,
        -3.503,
        2.367,
        -4.81,
        1,
        2.789,
        -6.152,
        3.211,
        -7,
        3.633,
        -7,
        2,
        7.367,
        -7,
        2,
        7.967,
        -7
      ]
    },
    {
      "Target": "Parameter",
      "Id": "ParamBodyAngleZ",
      "Segments": [
        0,
        0,
        0,
        1,
        9,
        0,
        1.467,
        3.08,
        0,
        2,
        9,
        0,
        3.567,
        -1.879,
        1,
        3.611,
        -1.879,
        3.656,
        -1.846,
        3.7,
        -1.828,
        1,
        3.8,
        -1.788,
        3.9,
        -1.779,
        4,
        -1.73,
        1,
        4.111,
        -1.676,
        4.222,
        -1.562,
        4.333,
        -1.44,
        1,
        4.566,
        -1.183,
        4.8,
        -0.998,
        5.033,
        -0.998,
        0,
        5.833,
        -6,
        1,
        5.955,
        -6,
        6.078,
        0.286,
        6.2,
        1.16,
        1,
        6.333,
        2.114,
        6.467,
        2,
        6.6,
        2,
        2,
        7.367,
        2,
        2,
        7.967,
        2
      ]
    },
    {
      "Target": "Parameter",
      "Id": "ParamHipY",
      "Segments": [
        0,
        0,
        2,
        4.167,
        0,
        0,
        5.833,
        -10,
        0,
        7.8,
        0,
        2,
        7.967,
        0
      ]
    },
    {
      "Target": "Parameter",
      "Id": "ParamLegL",
      "Segments": [
        0,
        0,
        2,
        1.667,
        0,
        0,
        2.567,
        -3,
        0,
        3.8,
        5,
        1,
        4.144,
        5,
        4.489,
        1.297,
        4.833,
        0,
        1,
        5.133,
        -1.13,
        5.433,
        -1,
        5.733,
        -1,
        0,
        7.767,
        0,
        2,
        7.967,
        0
      ]
    },
    {
      "Target": "Parameter",
      "Id": "ParamLegLY",
      "Segments": [
        0,
        0,
        2,
        1.667,
        0,
        0,
        2.567,
        10,
        0,
        3.8,
        -10,
        1,
        4.144,
        -10,
        4.489,
        -7.089,
        4.833,
        0,
        1,
        5.133,
        6.175,
        5.433,
        10,
        5.733,
        10,
        0,
        7.767,
        0,
        2,
        7.967,
        0
      ]
    },
    {
      "Target": "Parameter",
      "Id": "ParamLrgR",
      "Segments": [
        0,
        0,
        0,
        0.5,
        4,
        1,
        0.656,
        4,
        0.811,
        3.333,
        0.967,
        2,
        1,
        1.2,
        0,
        1.434,
        -1,
        1.667,
        -1,
        1,
        2.722,
        -1,
        3.778,
        -0.839,
        4.833,
        0,
        1,
        5.133,
        0.238,
        5.433,
        4,
        5.733,
        4,
        0,
        7.767,
        0,
        2,
        7.967,
        0
      ]
    },
    {
      "Target": "Parameter",
      "Id": "ParamLrgRY",
      "Segments": [
        0,
        0,
        2,
        0.5,
        0,
        0,
        0.967,
        -10,
        0,
        1.667,
        10,
        0,
        4.833,
        0,
        0,
        5.733,
        10,
        0,
        7.767,
        0,
        2,
        7.967,
        0
      ]
    },
    {
      "Target": "Parameter",
      "Id": "ParamEarL",
      "Segments": [
        0,
        0,
        0,
        0.567,
        1,
        0,
        1.533,
        -0.92,
        0,
        2.033,
        0.98,
        0,
        2.567,
        -1,
        0,
        3.367,
        1,
        0,
        4.2,
        -1,
        0,
        5.867,
        0,
        2,
        7.967,
        0
      ]
    },
    {
      "Target": "Parameter",
      "Id": "ParamEarR",
      "Segments": [
        0,
        0,
        0,
        0.567,
        1,
        0,
        1.533,
        -1,
        0,
        2.567,
        0.9,
        0,
        3.367,
        -1,
        0,
        4.2,
        1,
        0,
        5.867,
        0,
        2,
        7.967,
        0
      ]
    },
    {
      "Target": "Parameter",
      "Id": "ParamTailX",
      "Segments": [
        0,
        0,
        0,
        0.633,
        -1,
        0,
        1.567,
        0.71,
        1,
        1.756,
        0.71,
        1.944,
        -0.331,
        2.133,
        -0.35,
        1,
        2.366,
        -0.374,
        2.6,
        -0.37,
        2.833,
        -0.37,
        0,
        4.5,
        1,
        1,
        4.911,
        1,
        5.322,
        0.65,
        5.733,
        0.13,
        1,
        6.044,
        -0.264,
        6.356,
        -0.39,
        6.667,
        -0.39,
        0,
        7.767,
        0,
        2,
        7.967,
        0
      ]
    },
    {
      "Target": "Parameter",
      "Id": "ParamTailY",
      "Segments": [
        0,
        0,
        0,
        0.633,
        -1,
        0,
        1.567,
        1,
        1,
        1.756,
        1,
        1.944,
        0.8,
        2.133,
        0.21,
        1,
        2.366,
        -0.518,
        2.6,
        -1,
        2.833,
        -1,
        1,
        3.389,
        -1,
        3.944,
        -0.863,
        4.5,
        -0.17,
        1,
        4.911,
        0.343,
        5.322,
        1,
        5.733,
        1,
        0,
        6.667,
        -1,
        0,
        7.767,
        0,
        2,
        7.967,
        0
      ]
    },
    {
      "Target": "Model",
      "Id": "Opacity",
      "Segments": [
        0,
        1,
        0,
        7.97,
        1
      ]
    },
    {
      "Target": "Parameter",
      "Id": "ParamCheek",
      "Segments": [
        0,
        0,
        0,
        7.97,
        0
      ]
    },
    {
      "Target": "Parameter",
      "Id": "ParamBreath",
      "Segments": [
        0,
        0,
        0,
        7.97,
        0
      ]
    },
    {
      "Target": "Parameter",
      "Id": "ParamFingerL",
      "Segments": [
        0,
        0,
        0,
        7.97,
        0
      ]
    },
    {
      "Target": "Parameter",
      "Id": "ParamHandR",
      "Segments": [
        0,
        0,
        0,
        7.97,
        0
      ]
    },
    {
      "Target": "Parameter",
      "Id": "ParamFingerR",
      "Segments": [
        0,
        0,
        0,
        7.97,
        0
      ]
    },
    {
      "Target": "Parameter",
      "Id": "ParamHipX",
      "Segments": [
        0,
        0,
        0,
        7.97,
        0
      ]
    },
    {
      "Target": "Parameter",
      "Id": "ParamWX",
      "Segments": [
        0,
        0,
        0,
        7.97,
        0
      ]
    },
    {
      "Target": "Parameter",
      "Id": "ParamWY",
      "Segments": [
        0,
        0,
        0,
        7.97,
        0
      ]
    },
    {
      "Target": "Parameter",
      "Id": "ParamWZoom",
      "Segments": [
        0,
        0,
        0,
        7.97,
        0
      ]
    },
    {
      "Target": "Parameter",
      "Id": "ParamHairFront",
      "Segments": [
        0,
        0,
        0,
        7.97,
        0
      ]
    },
    {
      "Target": "Parameter",
      "Id": "ParamHairFrontY",
      "Segments": [
        0,
        0,
        0,
        7.97,
        0
      ]
    },
    {
      "Target": "Parameter",
      "Id": "ParamHairSide",
      "Segments": [
        0,
        0,
        0,
        7.97,
        0
      ]
    },
    {
      "Target": "Parameter",
      "Id": "ParamHairSideY",
      "Segments": [
        0,
        0,
        0,
        7.97,
        0
      ]
    },
    {
      "Target": "Parameter",
      "Id": "ParamHairBack",
      "Segments": [
        0,
        0,
        0,
        7.97,
        0
      ]
    },
    {
      "Target": "Parameter",
      "Id": "ParamHairBackY",
      "Segments": [
        0,
        0,
        0,
        7.97,
        0
      ]
    },
    {
      "Target": "Parameter",
      "Id": "ParamHairBack2",
      "Segments": [
        0,
        0,
        0,
        7.97,
        0
      ]
    },
    {
      "Target": "Parameter",
      "Id": "ParamHairBack2Y",
      "Segments": [
        0,
        0,
        0,
        7.97,
        0
      ]
    },
    {
      "Target": "Parameter",
      "Id": "ParamPiaodaiX",
      "Segments": [
        0,
        0,
        0,
        7.97,
        0
      ]
    },
    {
      "Target": "Parameter",
      "Id": "ParamPiaodaiY",
      "Segments": [
        0,
        0,
        0,
        7.97,
        0
      ]
    },
    {
      "Target": "Parameter",
      "Id": "ParamClothes",
      "Segments": [
        0,
        0,
        0,
        7.97,
        0
      ]
    },
    {
      "Target": "Parameter",
      "Id": "ParamClothesY",
      "Segments": [
        0,
        0,
        0,
        7.97,
        0
      ]
    },
    {
      "Target": "Parameter",
      "Id": "ParamBagX",
      "Segments": [
        0,
        0,
        0,
        7.97,
        0
      ]
    },
    {
      "Target": "Parameter",
      "Id": "ParamBagY",
      "Segments": [
        0,
        0,
        0,
        7.97,
        0
      ]
    },
    {
      "Target": "Parameter",
      "Id": "ParamMisk",
      "Segments": [
        0,
        0,
        0,
        7.97,
        0
      ]
    },
    {
      "Target": "Parameter",
      "Id": "ParamOpaishakeX",
      "Segments": [
        0,
        0,
        0,
        7.97,
        0
      ]
    },
    {
      "Target": "Parameter",
      "Id": "ParamOpaishakeY",
      "Segments": [
        0,
        0,
        0,
        7.97,
        0
      ]
    },
    {
      "Target": "Parameter",
      "Id": "ParamSkirt",
      "Segments": [
        0,
        0,
        0,
        7.97,
        0
      ]
    },
    {
      "Target": "Parameter",
      "Id": "ParamSkirtY",
      "Segments": [
        0,
        0,
        0,
        7.97,
        0
      ]
    }
  ],
  "UserData": [
    {
      "Time": 0.0,
      "Value": ""
    }
  ]
}