{
  "Version": 3,
  "Meta": {
    "Duration": 2.0,
    "Fps": 30.0,
    "Loop": true,
    "AreBeziersRestricted": true,
    "CurveCount": 175,
    "TotalSegmentCount": 191,
    "TotalPointCount": 211,
    "UserDataCount": 0,
    "TotalUserDataSize": 0
  },
  "Curves": [
    {
      "Target": "Parameter",
      "Id": "PARAM_ANGLE_Y",
      "Segments": [
        0,
        -15,
        1,
        0.111,
        -17.866,
        0.222,
        -19.234,
        0.333,
        -19.234,
        0,
        1.333,
        -6.335,
        1,
        1.555,
        -6.335,
        1.778,
        -9.268,
        2,
        -15
      ]
    },
    {
      "Target": "Parameter",
      "Id": "PARAM_ANGLE_Z",
      "Segments": [
        0,
        -15,
        0,
        1,
        -12.863,
        0,
        2,
        -15
      ]
    },
    {
      "Target": "Parameter",
      "Id": "PARAM_MOUTH_OPEN_Y",
      "Segments": [
        0,
        0,
        0,
        1,
        0.4,
        0,
        2,
        0
      ]
    },
    {
      "Target": "Parameter",
      "Id": "PARAM_MouthBig",
      "Segments": [
        0,
        -0.1,
        0,
        1,
        0,
        0,
        2,
        -0.1
      ]
    },
    {
      "Target": "Parameter",
      "Id": "PARAM_ShoulderL",
      "Segments": [
        0,
        0.3,
        1,
        0.333,
        0.389,
        0.667,
        0.5,
        1,
        0.5,
        1,
        1.333,
        0.5,
        1.667,
        0.389,
        2,
        0.3
      ]
    },
    {
      "Target": "Parameter",
      "Id": "PARAM_ShoulderR",
      "Segments": [
        0,
        0.3,
        1,
        0.333,
        0.389,
        0.667,
        0.5,
        1,
        0.5,
        1,
        1.333,
        0.5,
        1.667,
        0.389,
        2,
        0.3
      ]
    },
    {
      "Target": "Parameter",
      "Id": "PARAM_BODY_ANGLE_X",
      "Segments": [
        0,
        -3,
        1,
        0.167,
        -3.338,
        0.333,
        -3.506,
        0.5,
        -3.506,
        0,
        1.5,
        -2.492,
        1,
        1.667,
        -2.492,
        1.833,
        -2.662,
        2,
        -3
      ]
    },
    {
      "Target": "Parameter",
      "Id": "PARAM_BODY_ANGLE_Y",
      "Segments": [
        0,
        0,
        0,
        1,
        1,
        0,
        2,
        0
      ]
    },
    {
      "Target": "Parameter",
      "Id": "PARAM_BODY_ANGLE_Z",
      "Segments": [
        0,
        4,
        0,
        1,
        3,
        0,
        2,
        4
      ]
    },
    {
      "Target": "Parameter",
      "Id": "PARAM_BodyZplus",
      "Segments": [
        0,
        -3,
        0,
        1,
        -2,
        0,
        2,
        -3
      ]
    },
    {
      "Target": "Parameter",
      "Id": "PARAM_LegWave",
      "Segments": [
        0,
        3,
        1,
        0.167,
        2.665,
        0.333,
        2.499,
        0.5,
        2.499,
        0,
        1.5,
        3.503,
        1,
        1.667,
        3.503,
        1.833,
        3.335,
        2,
        3
      ]
    },
    {
      "Target": "Parameter",
      "Id": "PARAM_Total_Y",
      "Segments": [
        0,
        0,
        0,
        1,
        0.1,
        0,
        2,
        0
      ]
    },
    {
      "Target": "Parameter",
      "Id": "PARAM_ANGLE_X",
      "Segments": [
        0,
        -15.04,
        0,
        2,
        -15.04
      ]
    },
    {
      "Target": "Parameter",
      "Id": "PARAM_EYE_L_OPEN",
      "Segments": [
        0,
        0,
        0,
        2,
        0
      ]
    },
    {
      "Target": "Parameter",
      "Id": "PARAM_EYE_L_SMILE",
      "Segments": [
        0,
        0,
        0,
        2,
        0
      ]
    },
    {
      "Target": "Parameter",
      "Id": "PARAM_EYE_R_OPEN",
      "Segments": [
        0,
        0,
        0,
        2,
        0
      ]
    },
    {
      "Target": "Parameter",
      "Id": "PARAM_EYE_R_SMILE",
      "Segments": [
        0,
        0,
        0,
        2,
        0
      ]
    },
    {
      "Target": "Parameter",
      "Id": "PARAM_EYE_BALL_X",
      "Segments": [
        0,
        0.2,
        0,
        2,
        0.2
      ]
    },
    {
      "Target": "Parameter",
      "Id": "PARAM_EYE_BALL_Y",
      "Segments": [
        0,
        0,
        0,
        2,
        0
      ]
    },
    {
      "Target": "Parameter",
      "Id": "PARAM_EyeballSmall",
      "Segments": [
        0,
        0,
        0,
        2,
        0
      ]
    },
    {
      "Target": "Parameter",
      "Id": "PARAM_EyeballType",
      "Segments": [
        0,
        0,
        0,
        2,
        0
      ]
    },
    {
      "Target": "Parameter",
      "Id": "PARAM_Eyeball_TUAN",
      "Segments": [
        0,
        0,
        0,
        2,
        0
      ]
    },
    {
      "Target": "Parameter",
      "Id": "PARAM_Eyeball",
      "Segments": [
        0,
        0,
        0,
        2,
        0
      ]
    },
    {
      "Target": "Parameter",
      "Id": "PARAM_EyeType1",
      "Segments": [
        0,
        0,
        0,
        2,
        0
      ]
    },
    {
      "Target": "Parameter",
      "Id": "PARAM_EyeType2",
      "Segments": [
        0,
        0,
        0,
        2,
        0
      ]
    },
    {
      "Target": "Parameter",
      "Id": "PARAM_Tear",
      "Segments": [
        0,
        0,
        0,
        2,
        0
      ]
    },
    {
      "Target": "Parameter",
      "Id": "PARAM_Tear_liu",
      "Segments": [
        0,
        0,
        0,
        2,
        0
      ]
    },
    {
      "Target": "Parameter",
      "Id": "PARAM_BROW_L_X",
      "Segments": [
        0,
        0,
        0,
        2,
        0
      ]
    },
    {
      "Target": "Parameter",
      "Id": "PARAM_BROW_L_Y",
      "Segments": [
        0,
        -1,
        0,
        2,
        -1
      ]
    },
    {
      "Target": "Parameter",
      "Id": "PARAM_BROW_R_X",
      "Segments": [
        0,
        0,
        0,
        2,
        0
      ]
    },
    {
      "Target": "Parameter",
      "Id": "PARAM_BROW_R_Y",
      "Segments": [
        0,
        -1,
        0,
        2,
        -1
      ]
    },
    {
      "Target": "Parameter",
      "Id": "PARAM_BROW_L_ANGLE",
      "Segments": [
        0,
        0.2,
        0,
        2,
        0.2
      ]
    },
    {
      "Target": "Parameter",
      "Id": "PARAM_BROW_R_ANGLE",
      "Segments": [
        0,
        0.2,
        0,
        2,
        0.2
      ]
    },
    {
      "Target": "Parameter",
      "Id": "PARAM_BROW_L_FORM",
      "Segments": [
        0,
        -0.5,
        0,
        2,
        -0.5
      ]
    },
    {
      "Target": "Parameter",
      "Id": "PARAM_BROW_R_FORM",
      "Segments": [
        0,
        -0.5,
        0,
        2,
        -0.5
      ]
    },
    {
      "Target": "Parameter",
      "Id": "tooth_open",
      "Segments": [
        0,
        0.5,
        0,
        2,
        0.5
      ]
    },
    {
      "Target": "Parameter",
      "Id": "PARAM_MOUTH_FORM",
      "Segments": [
        0,
        1,
        0,
        2,
        1
      ]
    },
    {
      "Target": "Parameter",
      "Id": "PARAM_MouthWid",
      "Segments": [
        0,
        0,
        0,
        2,
        0
      ]
    },
    {
      "Target": "Parameter",
      "Id": "PARAM_Mouth_off",
      "Segments": [
        0,
        0,
        0,
        2,
        0
      ]
    },
    {
      "Target": "Parameter",
      "Id": "PARAM_MouthX",
      "Segments": [
        0,
        0,
        0,
        2,
        0
      ]
    },
    {
      "Target": "Parameter",
      "Id": "PARAM_MouthY",
      "Segments": [
        0,
        0,
        0,
        2,
        0
      ]
    },
    {
      "Target": "Parameter",
      "Id": "PARAM_MouthType1",
      "Segments": [
        0,
        0,
        0,
        2,
        0
      ]
    },
    {
      "Target": "Parameter",
      "Id": "PARAM_MouthType2",
      "Segments": [
        0,
        0,
        0,
        2,
        0
      ]
    },
    {
      "Target": "Parameter",
      "Id": "PARAM_FACE_du1",
      "Segments": [
        0,
        0,
        0,
        2,
        0
      ]
    },
    {
      "Target": "Parameter",
      "Id": "PARAM_FACE_du2",
      "Segments": [
        0,
        0,
        0,
        2,
        0
      ]
    },
    {
      "Target": "Parameter",
      "Id": "PARAM_CHEEK",
      "Segments": [
        0,
        0,
        0,
        2,
        0
      ]
    },
    {
      "Target": "Parameter",
      "Id": "PARAM_Cheek2",
      "Segments": [
        0,
        -1,
        0,
        2,
        -1
      ]
    },
    {
      "Target": "Parameter",
      "Id": "PARAM_BiPao",
      "Segments": [
        0,
        0,
        0,
        2,
        0
      ]
    },
    {
      "Target": "Parameter",
      "Id": "PARAM_Dark",
      "Segments": [
        0,
        0,
        0,
        2,
        0
      ]
    },
    {
      "Target": "Parameter",
      "Id": "PARAM_Line",
      "Segments": [
        0,
        0,
        0,
        2,
        0
      ]
    },
    {
      "Target": "Parameter",
      "Id": "PARAM_DARK_2",
      "Segments": [
        0,
        0,
        0,
        2,
        0
      ]
    },
    {
      "Target": "Parameter",
      "Id": "PARAM_Han",
      "Segments": [
        0,
        0,
        0,
        2,
        0
      ]
    },
    {
      "Target": "Parameter",
      "Id": "PARAM_Han_xh",
      "Segments": [
        0,
        0,
        0,
        2,
        0
      ]
    },
    {
      "Target": "Parameter",
      "Id": "PARAM_Zhamao",
      "Segments": [
        0,
        0,
        0,
        2,
        0
      ]
    },
    {
      "Target": "Parameter",
      "Id": "PARAM_OtherTyp1",
      "Segments": [
        0,
        0,
        0,
        2,
        0
      ]
    },
    {
      "Target": "Parameter",
      "Id": "PARAM_OtherTyp2",
      "Segments": [
        0,
        0,
        0,
        2,
        0
      ]
    },
    {
      "Target": "Parameter",
      "Id": "PARAM_Other",
      "Segments": [
        0,
        0,
        0,
        2,
        0
      ]
    },
    {
      "Target": "Parameter",
      "Id": "PARAM_FLOWER_ROLL",
      "Segments": [
        0,
        0,
        0,
        2,
        0
      ]
    },
    {
      "Target": "Parameter",
      "Id": "PARAM_Fire",
      "Segments": [
        0,
        0,
        0,
        2,
        0
      ]
    },
    {
      "Target": "Parameter",
      "Id": "PARAM_LEG_R",
      "Segments": [
        0,
        2,
        0,
        2,
        2
      ]
    },
    {
      "Target": "Parameter",
      "Id": "PARAM_LEG_L",
      "Segments": [
        0,
        -1.58,
        0,
        2,
        -1.58
      ]
    },
    {
      "Target": "Parameter",
      "Id": "PARAM_ArmR_bigRoll",
      "Segments": [
        0,
        -6.8,
        0,
        2,
        -6.8
      ]
    },
    {
      "Target": "Parameter",
      "Id": "PARAM_ArmRbigY",
      "Segments": [
        0,
        0.781,
        0,
        2,
        0.781
      ]
    },
    {
      "Target": "Parameter",
      "Id": "PARAM_ArmRsmallRoll",
      "Segments": [
        0,
        124.92,
        0,
        2,
        124.92
      ]
    },
    {
      "Target": "Parameter",
      "Id": "PARAM_ArmRSmall_Y",
      "Segments": [
        0,
        0.262,
        0,
        2,
        0.262
      ]
    },
    {
      "Target": "Parameter",
      "Id": "PARAM_ArmR_level",
      "Segments": [
        0,
        860.8,
        0,
        2,
        860.8
      ]
    },
    {
      "Target": "Parameter",
      "Id": "PARAM_HAND_R",
      "Segments": [
        0,
        4.208,
        0,
        2,
        4.208
      ]
    },
    {
      "Target": "Parameter",
      "Id": "PARAM_HAND_R_01",
      "Segments": [
        0,
        -1,
        0,
        2,
        -1
      ]
    },
    {
      "Target": "Parameter",
      "Id": "PARAM_SHIZHI_R",
      "Segments": [
        0,
        -1,
        0,
        2,
        -1
      ]
    },
    {
      "Target": "Parameter",
      "Id": "PARAM_ZHONGZHI_R",
      "Segments": [
        0,
        -1,
        0,
        2,
        -1
      ]
    },
    {
      "Target": "Parameter",
      "Id": "PARAM_WUMINGZHI_R",
      "Segments": [
        0,
        -1,
        0,
        2,
        -1
      ]
    },
    {
      "Target": "Parameter",
      "Id": "PARAM_XIAOZHI_R",
      "Segments": [
        0,
        -1,
        0,
        2,
        -1
      ]
    },
    {
      "Target": "Parameter",
      "Id": "PARAM_SHOUWAN_R",
      "Segments": [
        0,
        0.012,
        0,
        2,
        0.012
      ]
    },
    {
      "Target": "Parameter",
      "Id": "PARAM_ArmL_bigRoll",
      "Segments": [
        0,
        -14.4,
        0,
        2,
        -14.4
      ]
    },
    {
      "Target": "Parameter",
      "Id": "PARAM_ArmLbigY",
      "Segments": [
        0,
        0.88,
        0,
        2,
        0.88
      ]
    },
    {
      "Target": "Parameter",
      "Id": "PARAM_ArmLsmallRoll",
      "Segments": [
        0,
        115.52,
        0,
        2,
        115.52
      ]
    },
    {
      "Target": "Parameter",
      "Id": "PARAM_ArmLSmall_Y",
      "Segments": [
        0,
        0.304,
        0,
        2,
        0.304
      ]
    },
    {
      "Target": "Parameter",
      "Id": "PARAM_ArmL_level",
      "Segments": [
        0,
        900,
        0,
        2,
        900
      ]
    },
    {
      "Target": "Parameter",
      "Id": "PARAM_HAND_L",
      "Segments": [
        0,
        3.98,
        0,
        2,
        3.98
      ]
    },
    {
      "Target": "Parameter",
      "Id": "PARAM_HAND_L_01",
      "Segments": [
        0,
        -1,
        0,
        2,
        -1
      ]
    },
    {
      "Target": "Parameter",
      "Id": "PARAM_SHIZHI_L",
      "Segments": [
        0,
        -1,
        0,
        2,
        -1
      ]
    },
    {
      "Target": "Parameter",
      "Id": "PARAM_ZHONGZHI_L",
      "Segments": [
        0,
        -1,
        0,
        2,
        -1
      ]
    },
    {
      "Target": "Parameter",
      "Id": "PARAM_WUMINGZHI_L",
      "Segments": [
        0,
        -1,
        0,
        2,
        -1
      ]
    },
    {
      "Target": "Parameter",
      "Id": "PARAM_XIAOZHI_L",
      "Segments": [
        0,
        -1,
        0,
        2,
        -1
      ]
    },
    {
      "Target": "Parameter",
      "Id": "PARAM_SHOUWAN_L",
      "Segments": [
        0,
        0.03,
        0,
        2,
        0.03
      ]
    },
    {
      "Target": "Parameter",
      "Id": "PARAM_Total_X",
      "Segments": [
        0,
        0,
        0,
        2,
        0
      ]
    },
    {
      "Target": "Parameter",
      "Id": "PARAM_Total_Z",
      "Segments": [
        0,
        0,
        0,
        2,
        0
      ]
    },
    {
      "Target": "Parameter",
      "Id": "PARAM_BREATH",
      "Segments": [
        0,
        0,
        0,
        2,
        0
      ]
    },
    {
      "Target": "Parameter",
      "Id": "PARAM_XIANQUNZI",
      "Segments": [
        0,
        0,
        0,
        2,
        0
      ]
    },
    {
      "Target": "Parameter",
      "Id": "PARAM_XIANXIONGKOU",
      "Segments": [
        0,
        0,
        0,
        2,
        0
      ]
    },
    {
      "Target": "Parameter",
      "Id": "PARAM_LAHUDIEJIE",
      "Segments": [
        0,
        0,
        0,
        2,
        0
      ]
    },
    {
      "Target": "Parameter",
      "Id": "PARAM_CHEWAZI_R_01",
      "Segments": [
        0,
        0,
        0,
        2,
        0
      ]
    },
    {
      "Target": "Parameter",
      "Id": "PARAM_CHEWAZI_02",
      "Segments": [
        0,
        0,
        0,
        2,
        0
      ]
    },
    {
      "Target": "Parameter",
      "Id": "PARAM_CHEWAZI_L_01",
      "Segments": [
        0,
        0,
        0,
        2,
        0
      ]
    },
    {
      "Target": "Parameter",
      "Id": "PARAM_CHEWAZI_L_02",
      "Segments": [
        0,
        0,
        0,
        2,
        0
      ]
    },
    {
      "Target": "Parameter",
      "Id": "PARAM_",
      "Segments": [
        0,
        0,
        0,
        2,
        0
      ]
    },
    {
      "Target": "Parameter",
      "Id": "PARAM_DOLL",
      "Segments": [
        0,
        0,
        0,
        2,
        0
      ]
    },
    {
      "Target": "Parameter",
      "Id": "PARAM_DOLL02",
      "Segments": [
        0,
        0,
        0,
        2,
        0
      ]
    },
    {
      "Target": "Parameter",
      "Id": "PARAM_DOLL_ANGLE_X",
      "Segments": [
        0,
        0,
        0,
        2,
        0
      ]
    },
    {
      "Target": "Parameter",
      "Id": "PARAM_DOLL_ANGLE_Y",
      "Segments": [
        0,
        0,
        0,
        2,
        0
      ]
    },
    {
      "Target": "Parameter",
      "Id": "PARAM_DOLL_ANGLE_Z",
      "Segments": [
        0,
        0,
        0,
        2,
        0
      ]
    },
    {
      "Target": "Parameter",
      "Id": "PARAM_DOLL_X",
      "Segments": [
        0,
        0,
        0,
        2,
        0
      ]
    },
    {
      "Target": "Parameter",
      "Id": "PARAM_DOLL_Y",
      "Segments": [
        0,
        0,
        0,
        2,
        0
      ]
    },
    {
      "Target": "Parameter",
      "Id": "PARAM_DOLL_ROLL",
      "Segments": [
        0,
        0,
        0,
        2,
        0
      ]
    },
    {
      "Target": "Parameter",
      "Id": "PARAM_DOLL02_X",
      "Segments": [
        0,
        0,
        0,
        2,
        0
      ]
    },
    {
      "Target": "Parameter",
      "Id": "PARAM_DOLL02_Y",
      "Segments": [
        0,
        0,
        0,
        2,
        0
      ]
    },
    {
      "Target": "Parameter",
      "Id": "PARAM_DOLL02_ROLL",
      "Segments": [
        0,
        0,
        0,
        2,
        0
      ]
    },
    {
      "Target": "Parameter",
      "Id": "PARAM_DOLL_ARM_L_ROLL",
      "Segments": [
        0,
        0,
        0,
        2,
        0
      ]
    },
    {
      "Target": "Parameter",
      "Id": "PARAM_DOLL_ARM_L",
      "Segments": [
        0,
        0,
        0,
        2,
        0
      ]
    },
    {
      "Target": "Parameter",
      "Id": "PARAM_DOLL_ARM_R_ROLL",
      "Segments": [
        0,
        0,
        0,
        2,
        0
      ]
    },
    {
      "Target": "Parameter",
      "Id": "PARAM_DOLL_ARM_R",
      "Segments": [
        0,
        0,
        0,
        2,
        0
      ]
    },
    {
      "Target": "Parameter",
      "Id": "PARAM_DOLL_LEG_L_ROLL",
      "Segments": [
        0,
        0,
        0,
        2,
        0
      ]
    },
    {
      "Target": "Parameter",
      "Id": "PARAM_DOLL_LEGR_ROLL",
      "Segments": [
        0,
        0,
        0,
        2,
        0
      ]
    },
    {
      "Target": "Parameter",
      "Id": "PARAM_DOLL_EYE_TI1",
      "Segments": [
        0,
        0,
        0,
        2,
        0
      ]
    },
    {
      "Target": "Parameter",
      "Id": "PARAM_DOLL_EYE_TI2",
      "Segments": [
        0,
        0,
        0,
        2,
        0
      ]
    },
    {
      "Target": "Parameter",
      "Id": "PARAM_DOLL_EYE_AC",
      "Segments": [
        0,
        0,
        0,
        2,
        0
      ]
    },
    {
      "Target": "Parameter",
      "Id": "PARAM_DOLL_BIAOQING_TI1",
      "Segments": [
        0,
        0,
        0,
        2,
        0
      ]
    },
    {
      "Target": "Parameter",
      "Id": "PARAM_DOLL_TIAOQING_TI2",
      "Segments": [
        0,
        0,
        0,
        2,
        0
      ]
    },
    {
      "Target": "Parameter",
      "Id": "PARAM_DOLL_BIAOQING_AC",
      "Segments": [
        0,
        0,
        0,
        2,
        0
      ]
    },
    {
      "Target": "Parameter",
      "Id": "PARAM_DOLL_LEVEL",
      "Segments": [
        0,
        700,
        0,
        2,
        700
      ]
    },
    {
      "Target": "Parameter",
      "Id": "PARAM_HAIR_FRONT",
      "Segments": [
        0,
        0,
        0,
        2,
        0
      ]
    },
    {
      "Target": "Parameter",
      "Id": "PARAM_HAIR_SIDE",
      "Segments": [
        0,
        0,
        0,
        2,
        0
      ]
    },
    {
      "Target": "Parameter",
      "Id": "PARAM_HAIRFront_Wave",
      "Segments": [
        0,
        0,
        0,
        2,
        0
      ]
    },
    {
      "Target": "Parameter",
      "Id": "PARAM_HairQuanX",
      "Segments": [
        0,
        0,
        0,
        2,
        0
      ]
    },
    {
      "Target": "Parameter",
      "Id": "PARAM_HairQuanY",
      "Segments": [
        0,
        0,
        0,
        2,
        0
      ]
    },
    {
      "Target": "Parameter",
      "Id": "PARAM_HARISIDE_L_SHAKE1",
      "Segments": [
        0,
        0,
        0,
        2,
        0
      ]
    },
    {
      "Target": "Parameter",
      "Id": "PARAM_HARISIDE_L_SHAKE2",
      "Segments": [
        0,
        0,
        0,
        2,
        0
      ]
    },
    {
      "Target": "Parameter",
      "Id": "PARAM_HARISIDE_L_SHAKE3",
      "Segments": [
        0,
        0,
        0,
        2,
        0
      ]
    },
    {
      "Target": "Parameter",
      "Id": "PARAM_HARISIDE_R_SHAKE1",
      "Segments": [
        0,
        0,
        0,
        2,
        0
      ]
    },
    {
      "Target": "Parameter",
      "Id": "PARAM_HARISIDE_R_SHAKE2",
      "Segments": [
        0,
        0,
        0,
        2,
        0
      ]
    },
    {
      "Target": "Parameter",
      "Id": "PARAM_HARISIDE_R_SHAKE3",
      "Segments": [
        0,
        0,
        0,
        2,
        0
      ]
    },
    {
      "Target": "Parameter",
      "Id": "PARAM_HAIRBACK_R1_SHAKE1",
      "Segments": [
        0,
        0,
        0,
        2,
        0
      ]
    },
    {
      "Target": "Parameter",
      "Id": "PARAM_HAIRBACK_R1_SHAKE2",
      "Segments": [
        0,
        0,
        0,
        2,
        0
      ]
    },
    {
      "Target": "Parameter",
      "Id": "PARAM_HAIRBACK_R1_SHAKE3",
      "Segments": [
        0,
        0,
        0,
        2,
        0
      ]
    },
    {
      "Target": "Parameter",
      "Id": "PARAM_HAIRBACK_R1_SHAKE4",
      "Segments": [
        0,
        0,
        0,
        2,
        0
      ]
    },
    {
      "Target": "Parameter",
      "Id": "PARAM_HAIRBACK_R2_SHAKE1",
      "Segments": [
        0,
        0,
        0,
        2,
        0
      ]
    },
    {
      "Target": "Parameter",
      "Id": "PARAM_HAIRBACK_R2_SHAKE2",
      "Segments": [
        0,
        0,
        0,
        2,
        0
      ]
    },
    {
      "Target": "Parameter",
      "Id": "PARAM_HAIRBACK_R2_SHAKE3",
      "Segments": [
        0,
        0,
        0,
        2,
        0
      ]
    },
    {
      "Target": "Parameter",
      "Id": "PARAM_HAIRBACK_R3_SHAKE1",
      "Segments": [
        0,
        0,
        0,
        2,
        0
      ]
    },
    {
      "Target": "Parameter",
      "Id": "PARAM_HAIRBACK_R3_SHAKE2",
      "Segments": [
        0,
        0,
        0,
        2,
        0
      ]
    },
    {
      "Target": "Parameter",
      "Id": "PARAM_HAIRBACK_R3_SHAKE3",
      "Segments": [
        0,
        0,
        0,
        2,
        0
      ]
    },
    {
      "Target": "Parameter",
      "Id": "PARAM_HAIRBACK_L1_SHAKE1",
      "Segments": [
        0,
        0,
        0,
        2,
        0
      ]
    },
    {
      "Target": "Parameter",
      "Id": "PARAM_HAIRBACK_L1_SHAKE2",
      "Segments": [
        0,
        0,
        0,
        2,
        0
      ]
    },
    {
      "Target": "Parameter",
      "Id": "PARAM_HAIRBACK_L1_SHAKE3",
      "Segments": [
        0,
        0,
        0,
        2,
        0
      ]
    },
    {
      "Target": "Parameter",
      "Id": "PARAM_HAIRBACK_L1_SHAKE4",
      "Segments": [
        0,
        0,
        0,
        2,
        0
      ]
    },
    {
      "Target": "Parameter",
      "Id": "PARAM_HAIRBACK_L2_SHAKE1",
      "Segments": [
        0,
        0,
        0,
        2,
        0
      ]
    },
    {
      "Target": "Parameter",
      "Id": "PARAM_HAIRBACK_L2_SHAKE2",
      "Segments": [
        0,
        0,
        0,
        2,
        0
      ]
    },
    {
      "Target": "Parameter",
      "Id": "PARAM_HAIRBACK_L2_SHAKE3",
      "Segments": [
        0,
        0,
        0,
        2,
        0
      ]
    },
    {
      "Target": "Parameter",
      "Id": "PARAM_HAIRBACK_L3_SHAKE1",
      "Segments": [
        0,
        0,
        0,
        2,
        0
      ]
    },
    {
      "Target": "Parameter",
      "Id": "PARAM_HAIRBACK_L3_SHAKE2",
      "Segments": [
        0,
        0,
        0,
        2,
        0
      ]
    },
    {
      "Target": "Parameter",
      "Id": "PARAM_HAIRBACK_L3_SHAKE3",
      "Segments": [
        0,
        0,
        0,
        2,
        0
      ]
    },
    {
      "Target": "Parameter",
      "Id": "PARAM_BUST_X",
      "Segments": [
        0,
        0,
        0,
        2,
        0
      ]
    },
    {
      "Target": "Parameter",
      "Id": "PARAM_BUST_Y",
      "Segments": [
        0,
        0,
        0,
        2,
        0
      ]
    },
    {
      "Target": "Parameter",
      "Id": "PARAM_QUNZI_01",
      "Segments": [
        0,
        0,
        0,
        2,
        0
      ]
    },
    {
      "Target": "Parameter",
      "Id": "PARAM_QUNZI_02",
      "Segments": [
        0,
        0,
        0,
        2,
        0
      ]
    },
    {
      "Target": "Parameter",
      "Id": "PARAM_XIONGKOU_DAIZI_02",
      "Segments": [
        0,
        0,
        0,
        2,
        0
      ]
    },
    {
      "Target": "Parameter",
      "Id": "PARAM_XIONGKOU_DAIZI_03",
      "Segments": [
        0,
        0,
        0,
        2,
        0
      ]
    },
    {
      "Target": "Parameter",
      "Id": "PARAM_XIONGKOU_DAIZI_04",
      "Segments": [
        0,
        0,
        0,
        2,
        0
      ]
    },
    {
      "Target": "Parameter",
      "Id": "PARAM_HUDIEJIE_01",
      "Segments": [
        0,
        0,
        0,
        2,
        0
      ]
    },
    {
      "Target": "Parameter",
      "Id": "PARAM_HUDIEJIE_02",
      "Segments": [
        0,
        0,
        0,
        2,
        0
      ]
    },
    {
      "Target": "Parameter",
      "Id": "PARAM_HUDIEJIE_03",
      "Segments": [
        0,
        0,
        0,
        2,
        0
      ]
    },
    {
      "Target": "Parameter",
      "Id": "PARAM_HUDIEJIE_04",
      "Segments": [
        0,
        0,
        0,
        2,
        0
      ]
    },
    {
      "Target": "Parameter",
      "Id": "PARAM_HUDIEJIE_05",
      "Segments": [
        0,
        0,
        0,
        2,
        0
      ]
    },
    {
      "Target": "Parameter",
      "Id": "PARAM_HUDIEJIE_06",
      "Segments": [
        0,
        0,
        0,
        2,
        0
      ]
    },
    {
      "Target": "Parameter",
      "Id": "PARAM_XIUZI_PIAODAI_01",
      "Segments": [
        0,
        0,
        0,
        2,
        0
      ]
    },
    {
      "Target": "Parameter",
      "Id": "PARAM_XIUZI_PIAODAI_01_2",
      "Segments": [
        0,
        0,
        0,
        2,
        0
      ]
    },
    {
      "Target": "Parameter",
      "Id": "PARAM_XIUZI_PIAODAI_02",
      "Segments": [
        0,
        0,
        0,
        2,
        0
      ]
    },
    {
      "Target": "Parameter",
      "Id": "PARAM_XIUZI_PIAODAI_02_2",
      "Segments": [
        0,
        0,
        0,
        2,
        0
      ]
    },
    {
      "Target": "Parameter",
      "Id": "PARAM_XIUZI_PIAODAI_03",
      "Segments": [
        0,
        0,
        0,
        2,
        0
      ]
    },
    {
      "Target": "Parameter",
      "Id": "PARAM_XIUZI_PIAODAI_03_2",
      "Segments": [
        0,
        0,
        0,
        2,
        0
      ]
    },
    {
      "Target": "Parameter",
      "Id": "PARAM_XIUZI_PIAODAI_04",
      "Segments": [
        0,
        0,
        0,
        2,
        0
      ]
    },
    {
      "Target": "Parameter",
      "Id": "PARAM_XIUZI_PIAODAI_04_2",
      "Segments": [
        0,
        0,
        0,
        2,
        0
      ]
    },
    {
      "Target": "Parameter",
      "Id": "PARAM_XIUZI_HUDIEJIE_R",
      "Segments": [
        0,
        0,
        0,
        2,
        0
      ]
    },
    {
      "Target": "Parameter",
      "Id": "PARAM_XIUZI_HUDIEJIE_L",
      "Segments": [
        0,
        0,
        0,
        2,
        0
      ]
    },
    {
      "Target": "Parameter",
      "Id": "PARAM_XIUZI_HUDIEJIE_L_02",
      "Segments": [
        0,
        0,
        0,
        2,
        0
      ]
    }
  ],
  "UserData": []
}